{"dependencies":[{"name":"/Users/gauthier/Documents/Server/muse-ui/src/styles/import.less","includedInParent":true,"mtime":1521141756295},{"name":"/Users/gauthier/Documents/Server/muse-ui/src/styles/vars.less","includedInParent":true,"mtime":1521141756296},{"name":"/Users/gauthier/Documents/Server/muse-ui/src/styles/mixins.less","includedInParent":true,"mtime":1521141025945},{"name":"/Users/gauthier/Documents/Server/muse-ui/src/styles/colors.less","includedInParent":true,"mtime":1521141025945},{"name":"/Users/gauthier/Documents/Server/muse-ui/.postcssrc.js","includedInParent":true,"mtime":1521141756257},{"name":"_css_loader"}],"generated":{"css":".mu-input {\n  font-size: 16px;\n  width: 256px;\n  min-height: 48px;\n  display: inline-block;\n  position: relative;\n  color: rgba(0, 0, 0, 0.54);\n  margin-bottom: 8px;\n}\n.mu-input.full-width {\n  width: 100%;\n}\n.mu-input.has-icon {\n  padding-left: 56px;\n}\n.mu-input.focus-state {\n  color: #2196f3;\n}\n.mu-input.error {\n  color: #f44336;\n}\n.mu-input.has-label {\n  min-height: 72px;\n}\n.mu-input-icon {\n  position: absolute;\n  left: 16px;\n  top: 8px;\n}\n.mu-input.has-label .mu-input-icon {\n  top: 32px;\n}\n.mu-input-content {\n  display: block;\n  height: 100%;\n  padding-bottom: 12px;\n  padding-top: 4px;\n}\n.mu-input.disabled .mu-input-content {\n  color: rgba(0, 0, 0, 0.38);\n  cursor: not-allowed;\n}\n.mu-input.has-label .mu-input-content {\n  padding-top: 28px;\n  padding-bottom: 12px;\n}\n.mu-input-help {\n  position: absolute;\n  margin-top: 6px;\n  font-size: 12px;\n  line-height: 12px;\n  color: rgba(0, 0, 0, 0.54);\n  display: -webkit-box;\n  display: -webkit-flex;\n  display: -ms-flexbox;\n  display: flex;\n  -webkit-box-pack: justify;\n  -webkit-justify-content: space-between;\n      -ms-flex-pack: justify;\n          justify-content: space-between;\n  left: 0;\n  right: 0;\n}\n.mu-input.has-icon .mu-input-help {\n  left: 56px;\n}\n.mu-input.error .mu-input-help {\n  color: #f44336;\n}\n.mu-input.disabled .mu-input-help {\n  color: inherit;\n}\n.mu-input-label {\n  line-height: 20px;\n  -webkit-transition: all 0.45s cubic-bezier(0.23, 1, 0.32, 1);\n  -o-transition: all 0.45s cubic-bezier(0.23, 1, 0.32, 1);\n  transition: all 0.45s cubic-bezier(0.23, 1, 0.32, 1);\n  z-index: 1;\n  cursor: text;\n  -webkit-transform: translate3d(0, 0, 0) scale(0.75);\n          transform: translate3d(0, 0, 0) scale(0.75);\n  -webkit-transform-origin: left top;\n          transform-origin: left top;\n  -webkit-user-select: none;\n     -moz-user-select: none;\n      -ms-user-select: none;\n          user-select: none;\n  pointer-events: none;\n  -webkit-backface-visibility: hidden;\n          backface-visibility: hidden;\n}\n.mu-input.has-label .mu-input-label {\n  top: 8px;\n  position: absolute;\n}\n.mu-input.has-label .mu-input-label.float {\n  -webkit-transform: translate3d(0, 28px, 0) scale(1);\n          transform: translate3d(0, 28px, 0) scale(1);\n  color: rgba(0, 0, 0, 0.38);\n}\n.mu-input-line {\n  margin: 0;\n  height: 1px;\n  border: none;\n  background-color: rgba(0, 0, 0, 0.12);\n  left: 0;\n  right: 0;\n  bottom: 12px;\n  position: absolute;\n}\n.mu-input.has-icon .mu-input-line {\n  left: 56px;\n}\n.mu-input-line.disabled {\n  height: auto;\n  background-color: transparent;\n  border-bottom: 2px dotted rgba(0, 0, 0, 0.38);\n}\n.mu-input-focus-line {\n  margin: 0;\n  height: 2px;\n  border: none;\n  background-color: #2196f3;\n  position: absolute;\n  left: 0;\n  right: 0;\n  bottom: 12px;\n  margin-top: -1px;\n  -webkit-transform: scaleX(0);\n          transform: scaleX(0);\n  -webkit-transition: -webkit-transform 0.45s cubic-bezier(0.23, 1, 0.32, 1);\n  transition: -webkit-transform 0.45s cubic-bezier(0.23, 1, 0.32, 1);\n  -o-transition: transform 0.45s cubic-bezier(0.23, 1, 0.32, 1);\n  transition: transform 0.45s cubic-bezier(0.23, 1, 0.32, 1);\n  transition: transform 0.45s cubic-bezier(0.23, 1, 0.32, 1), -webkit-transform 0.45s cubic-bezier(0.23, 1, 0.32, 1);\n}\n.mu-input.has-icon .mu-input-focus-line {\n  left: 56px;\n}\n.mu-input-focus-line.focus {\n  -webkit-transform: scaleX(1);\n          transform: scaleX(1);\n}\n.mu-input-focus-line.error {\n  -webkit-transform: scaleX(1);\n          transform: scaleX(1);\n  background-color: #f44336;\n}\n","js":"\n        var reloadCSS = require('_css_loader');\n        module.hot.dispose(reloadCSS);\n        module.hot.accept(reloadCSS);\n      "},"hash":"82fb09e109d6dd9ca84e8f5573e060cf","cacheData":{}}