{"dependencies":[{"name":"/Users/gauthier/Documents/Server/muse-ui/.babelrc","includedInParent":true,"mtime":1521141756256},{"name":"/Users/gauthier/Documents/Server/muse-ui/package.json","includedInParent":true,"mtime":1521141801298},{"name":"../styles/components/date-picker.less","loc":{"line":1,"column":7}},{"name":"./DatePicker","loc":{"line":2,"column":23}}],"generated":{"js":"'use strict';\n\nObject.defineProperty(exports, \"__esModule\", {\n  value: true\n});\n\nrequire('../styles/components/date-picker.less');\n\nvar _DatePicker = require('./DatePicker');\n\nvar _DatePicker2 = _interopRequireDefault(_DatePicker);\n\nfunction _interopRequireDefault(obj) { return obj && obj.__esModule ? obj : { default: obj }; }\n\n_DatePicker2.default.install = function (Vue) {\n  Vue.component(_DatePicker2.default.name, _DatePicker2.default);\n};\n\nexports.default = _DatePicker2.default;","map":{"mappings":[{"generated":{"line":7,"column":0},"source":"../src/DatePicker/index.js","original":{"line":1,"column":0}},{"generated":{"line":9,"column":0},"source":"../src/DatePicker/index.js","original":{"line":2,"column":0}},{"generated":{"line":15,"column":0},"source":"../src/DatePicker/index.js","original":{"line":4,"column":0}},{"name":"install","generated":{"line":15,"column":21},"source":"../src/DatePicker/index.js","original":{"line":4,"column":11}},{"generated":{"line":15,"column":28},"source":"../src/DatePicker/index.js","original":{"line":4,"column":0}},{"generated":{"line":15,"column":31},"source":"../src/DatePicker/index.js","original":{"line":4,"column":21}},{"name":"Vue","generated":{"line":15,"column":41},"source":"../src/DatePicker/index.js","original":{"line":4,"column":31}},{"generated":{"line":15,"column":44},"source":"../src/DatePicker/index.js","original":{"line":4,"column":21}},{"generated":{"line":15,"column":46},"source":"../src/DatePicker/index.js","original":{"line":4,"column":36}},{"name":"Vue","generated":{"line":16,"column":0},"source":"../src/DatePicker/index.js","original":{"line":5,"column":2}},{"name":"component","generated":{"line":16,"column":6},"source":"../src/DatePicker/index.js","original":{"line":5,"column":6}},{"generated":{"line":16,"column":15},"source":"../src/DatePicker/index.js","original":{"line":5,"column":2}},{"generated":{"line":16,"column":16},"source":"../src/DatePicker/index.js","original":{"line":5,"column":16}},{"name":"name","generated":{"line":16,"column":37},"source":"../src/DatePicker/index.js","original":{"line":5,"column":27}},{"generated":{"line":16,"column":41},"source":"../src/DatePicker/index.js","original":{"line":5,"column":2}},{"generated":{"line":17,"column":0},"source":"../src/DatePicker/index.js","original":{"line":6,"column":1}},{"generated":{"line":17,"column":1},"source":"../src/DatePicker/index.js","original":{"line":4,"column":0}}],"sources":{"../src/DatePicker/index.js":"import '../styles/components/date-picker.less';\r\nimport DatePicker from './DatePicker';\r\n\r\nDatePicker.install = function (Vue) {\r\n  Vue.component(DatePicker.name, DatePicker);\r\n};\r\n\r\nexport default DatePicker;\r\n"},"lineCount":null}},"hash":"edb8f086d0fc4ea3b11d81636c5ec4f2","cacheData":{"env":{}}}