{"dependencies":[{"name":"/Users/gauthier/Documents/Server/muse-ui/.babelrc","includedInParent":true,"mtime":1521141756256},{"name":"/Users/gauthier/Documents/Server/muse-ui/package.json","includedInParent":true,"mtime":1521141801298},{"name":"vue","loc":{"line":1,"column":16}},{"name":"./TooltipContent","loc":{"line":2,"column":27}},{"name":"../utils","loc":{"line":3,"column":39}}],"generated":{"js":"'use strict';\n\nObject.defineProperty(exports, \"__esModule\", {\n  value: true\n});\n\nvar _vue = require('vue');\n\nvar _vue2 = _interopRequireDefault(_vue);\n\nvar _TooltipContent = require('./TooltipContent');\n\nvar _TooltipContent2 = _interopRequireDefault(_TooltipContent);\n\nvar _utils = require('../utils');\n\nfunction _interopRequireDefault(obj) { return obj && obj.__esModule ? obj : { default: obj }; }\n\nexports.default = {\n  name: 'mu-tooltip',\n  props: {\n    content: String,\n    placement: _TooltipContent2.default.props.placement,\n    open: Boolean,\n    tooltipClass: [String, Object, Array]\n  },\n  data: function data() {\n    return {\n      active: this.open,\n      trigger: null\n    };\n  },\n  beforeCreate: function beforeCreate() {\n    if (this.$isServer) return;\n\n    this.tooltipVM = new _vue2.default({\n      data: { node: '' },\n      render: function render(h) {\n        return this.node;\n      }\n    }).$mount();\n  },\n  mounted: function mounted() {\n    this.trigger = this.$el;\n  },\n\n  methods: {\n    addEventHandle: function addEventHandle(old, fn) {\n      if (!old) {\n        return fn;\n      } else if (Array.isArray(old)) {\n        return old.indexOf(fn) > -1 ? old : old.concat(fn);\n      } else {\n        return old === fn ? old : [old, fn];\n      }\n    },\n    show: function show() {\n      if (this.timer) clearTimeout(this.timer);\n      this.active = true;\n    },\n    hide: function hide() {\n      var _this = this;\n\n      if (this.timer) clearTimeout(this.timer);\n      this.timer = setTimeout(function () {\n        _this.active = false;\n      }, 200);\n    }\n  },\n  watch: {\n    active: function active(val) {\n      this.$emit('update:open', val);\n    },\n    open: function open(val) {\n      this.active = val;\n    }\n  },\n  render: function render(h) {\n    var _this2 = this;\n\n    var content = (this.$slots.content && this.$slots.content.length > 0 ? this.$slots.content : this.content) || '';\n    this.tooltipVM.node = h(_TooltipContent2.default, {\n      class: this.tooltipClass,\n      props: {\n        placement: this.placement,\n        open: this.active,\n        trigger: this.trigger\n      },\n      nativeOn: {\n        mouseenter: function mouseenter() {\n          return _this2.show();\n        },\n        mouseleave: function mouseleave() {\n          return _this2.hide();\n        }\n      }\n    }, content);\n\n    var vnode = (0, _utils.getFirstComponentChild)(this.$slots.default);\n    if (!vnode) return vnode;\n\n    var on = vnode.data.on = vnode.data.on || {};\n    var nativeOn = vnode.data.nativeOn = vnode.data.nativeOn || {};\n    nativeOn.mouseenter = on.mouseenter = this.addEventHandle(on.mouseenter, this.show);\n    nativeOn.mouseleave = on.mouseleave = this.addEventHandle(on.mouseleave, this.hide);\n    return vnode;\n  }\n};","map":{"mappings":[{"generated":{"line":7,"column":0},"source":"../src/Tooltip/Tooltip.js","original":{"line":1,"column":0}},{"generated":{"line":11,"column":0},"source":"../src/Tooltip/Tooltip.js","original":{"line":2,"column":0}},{"generated":{"line":15,"column":0},"source":"../src/Tooltip/Tooltip.js","original":{"line":3,"column":0}},{"generated":{"line":19,"column":18},"source":"../src/Tooltip/Tooltip.js","original":{"line":5,"column":15}},{"name":"name","generated":{"line":20,"column":0},"source":"../src/Tooltip/Tooltip.js","original":{"line":6,"column":2}},{"generated":{"line":20,"column":8},"source":"../src/Tooltip/Tooltip.js","original":{"line":6,"column":8}},{"generated":{"line":20,"column":20},"source":"../src/Tooltip/Tooltip.js","original":{"line":5,"column":15}},{"name":"props","generated":{"line":21,"column":0},"source":"../src/Tooltip/Tooltip.js","original":{"line":7,"column":2}},{"generated":{"line":21,"column":9},"source":"../src/Tooltip/Tooltip.js","original":{"line":7,"column":9}},{"name":"content","generated":{"line":22,"column":0},"source":"../src/Tooltip/Tooltip.js","original":{"line":8,"column":4}},{"name":"String","generated":{"line":22,"column":13},"source":"../src/Tooltip/Tooltip.js","original":{"line":8,"column":13}},{"generated":{"line":22,"column":19},"source":"../src/Tooltip/Tooltip.js","original":{"line":7,"column":9}},{"name":"placement","generated":{"line":23,"column":0},"source":"../src/Tooltip/Tooltip.js","original":{"line":9,"column":4}},{"generated":{"line":23,"column":15},"source":"../src/Tooltip/Tooltip.js","original":{"line":9,"column":15}},{"name":"props","generated":{"line":23,"column":40},"source":"../src/Tooltip/Tooltip.js","original":{"line":9,"column":30}},{"generated":{"line":23,"column":45},"source":"../src/Tooltip/Tooltip.js","original":{"line":9,"column":15}},{"name":"placement","generated":{"line":23,"column":46},"source":"../src/Tooltip/Tooltip.js","original":{"line":9,"column":36}},{"generated":{"line":23,"column":55},"source":"../src/Tooltip/Tooltip.js","original":{"line":7,"column":9}},{"name":"open","generated":{"line":24,"column":0},"source":"../src/Tooltip/Tooltip.js","original":{"line":10,"column":4}},{"name":"Boolean","generated":{"line":24,"column":10},"source":"../src/Tooltip/Tooltip.js","original":{"line":10,"column":10}},{"generated":{"line":24,"column":17},"source":"../src/Tooltip/Tooltip.js","original":{"line":7,"column":9}},{"name":"tooltipClass","generated":{"line":25,"column":0},"source":"../src/Tooltip/Tooltip.js","original":{"line":11,"column":4}},{"generated":{"line":25,"column":18},"source":"../src/Tooltip/Tooltip.js","original":{"line":11,"column":18}},{"name":"String","generated":{"line":25,"column":19},"source":"../src/Tooltip/Tooltip.js","original":{"line":11,"column":19}},{"generated":{"line":25,"column":25},"source":"../src/Tooltip/Tooltip.js","original":{"line":11,"column":18}},{"name":"Object","generated":{"line":25,"column":27},"source":"../src/Tooltip/Tooltip.js","original":{"line":11,"column":27}},{"generated":{"line":25,"column":33},"source":"../src/Tooltip/Tooltip.js","original":{"line":11,"column":18}},{"name":"Array","generated":{"line":25,"column":35},"source":"../src/Tooltip/Tooltip.js","original":{"line":11,"column":35}},{"generated":{"line":25,"column":40},"source":"../src/Tooltip/Tooltip.js","original":{"line":11,"column":18}},{"generated":{"line":26,"column":0},"source":"../src/Tooltip/Tooltip.js","original":{"line":7,"column":9}},{"generated":{"line":26,"column":3},"source":"../src/Tooltip/Tooltip.js","original":{"line":5,"column":15}},{"name":"data","generated":{"line":27,"column":0},"source":"../src/Tooltip/Tooltip.js","original":{"line":13,"column":2}},{"generated":{"line":27,"column":6},"source":"../src/Tooltip/Tooltip.js","original":{"line":5,"column":15}},{"generated":{"line":27,"column":24},"source":"../src/Tooltip/Tooltip.js","original":{"line":13,"column":10}},{"generated":{"line":28,"column":0},"source":"../src/Tooltip/Tooltip.js","original":{"line":14,"column":4}},{"generated":{"line":28,"column":11},"source":"../src/Tooltip/Tooltip.js","original":{"line":14,"column":11}},{"name":"active","generated":{"line":29,"column":0},"source":"../src/Tooltip/Tooltip.js","original":{"line":15,"column":6}},{"generated":{"line":29,"column":14},"source":"../src/Tooltip/Tooltip.js","original":{"line":15,"column":14}},{"name":"open","generated":{"line":29,"column":19},"source":"../src/Tooltip/Tooltip.js","original":{"line":15,"column":19}},{"generated":{"line":29,"column":23},"source":"../src/Tooltip/Tooltip.js","original":{"line":14,"column":11}},{"name":"trigger","generated":{"line":30,"column":0},"source":"../src/Tooltip/Tooltip.js","original":{"line":16,"column":6}},{"generated":{"line":30,"column":15},"source":"../src/Tooltip/Tooltip.js","original":{"line":16,"column":15}},{"generated":{"line":31,"column":0},"source":"../src/Tooltip/Tooltip.js","original":{"line":14,"column":11}},{"generated":{"line":31,"column":5},"source":"../src/Tooltip/Tooltip.js","original":{"line":14,"column":4}},{"generated":{"line":32,"column":0},"source":"../src/Tooltip/Tooltip.js","original":{"line":18,"column":3}},{"generated":{"line":32,"column":3},"source":"../src/Tooltip/Tooltip.js","original":{"line":5,"column":15}},{"name":"beforeCreate","generated":{"line":33,"column":0},"source":"../src/Tooltip/Tooltip.js","original":{"line":19,"column":2}},{"generated":{"line":33,"column":14},"source":"../src/Tooltip/Tooltip.js","original":{"line":5,"column":15}},{"generated":{"line":33,"column":40},"source":"../src/Tooltip/Tooltip.js","original":{"line":19,"column":18}},{"generated":{"line":34,"column":0},"source":"../src/Tooltip/Tooltip.js","original":{"line":20,"column":4}},{"generated":{"line":34,"column":8},"source":"../src/Tooltip/Tooltip.js","original":{"line":20,"column":8}},{"name":"$isServer","generated":{"line":34,"column":13},"source":"../src/Tooltip/Tooltip.js","original":{"line":20,"column":13}},{"generated":{"line":34,"column":22},"source":"../src/Tooltip/Tooltip.js","original":{"line":20,"column":4}},{"generated":{"line":34,"column":24},"source":"../src/Tooltip/Tooltip.js","original":{"line":20,"column":24}},{"generated":{"line":36,"column":0},"source":"../src/Tooltip/Tooltip.js","original":{"line":22,"column":4}},{"name":"tooltipVM","generated":{"line":36,"column":9},"source":"../src/Tooltip/Tooltip.js","original":{"line":22,"column":9}},{"generated":{"line":36,"column":18},"source":"../src/Tooltip/Tooltip.js","original":{"line":22,"column":4}},{"generated":{"line":36,"column":21},"source":"../src/Tooltip/Tooltip.js","original":{"line":22,"column":21}},{"generated":{"line":36,"column":39},"source":"../src/Tooltip/Tooltip.js","original":{"line":22,"column":29}},{"name":"data","generated":{"line":37,"column":0},"source":"../src/Tooltip/Tooltip.js","original":{"line":23,"column":6}},{"generated":{"line":37,"column":12},"source":"../src/Tooltip/Tooltip.js","original":{"line":23,"column":12}},{"name":"node","generated":{"line":37,"column":14},"source":"../src/Tooltip/Tooltip.js","original":{"line":23,"column":14}},{"generated":{"line":37,"column":20},"source":"../src/Tooltip/Tooltip.js","original":{"line":23,"column":20}},{"generated":{"line":37,"column":22},"source":"../src/Tooltip/Tooltip.js","original":{"line":23,"column":12}},{"generated":{"line":37,"column":24},"source":"../src/Tooltip/Tooltip.js","original":{"line":22,"column":29}},{"name":"render","generated":{"line":38,"column":0},"source":"../src/Tooltip/Tooltip.js","original":{"line":24,"column":6}},{"generated":{"line":38,"column":12},"source":"../src/Tooltip/Tooltip.js","original":{"line":22,"column":29}},{"name":"h","generated":{"line":38,"column":30},"source":"../src/Tooltip/Tooltip.js","original":{"line":24,"column":14}},{"generated":{"line":38,"column":31},"source":"../src/Tooltip/Tooltip.js","original":{"line":22,"column":29}},{"generated":{"line":38,"column":33},"source":"../src/Tooltip/Tooltip.js","original":{"line":24,"column":17}},{"generated":{"line":39,"column":0},"source":"../src/Tooltip/Tooltip.js","original":{"line":25,"column":8}},{"generated":{"line":39,"column":15},"source":"../src/Tooltip/Tooltip.js","original":{"line":25,"column":15}},{"name":"node","generated":{"line":39,"column":20},"source":"../src/Tooltip/Tooltip.js","original":{"line":25,"column":20}},{"generated":{"line":39,"column":24},"source":"../src/Tooltip/Tooltip.js","original":{"line":25,"column":8}},{"generated":{"line":40,"column":0},"source":"../src/Tooltip/Tooltip.js","original":{"line":26,"column":7}},{"generated":{"line":41,"column":0},"source":"../src/Tooltip/Tooltip.js","original":{"line":22,"column":29}},{"generated":{"line":41,"column":5},"source":"../src/Tooltip/Tooltip.js","original":{"line":22,"column":21}},{"name":"$mount","generated":{"line":41,"column":7},"source":"../src/Tooltip/Tooltip.js","original":{"line":27,"column":7}},{"generated":{"line":41,"column":13},"source":"../src/Tooltip/Tooltip.js","original":{"line":22,"column":21}},{"generated":{"line":41,"column":15},"source":"../src/Tooltip/Tooltip.js","original":{"line":22,"column":4}},{"generated":{"line":42,"column":0},"source":"../src/Tooltip/Tooltip.js","original":{"line":28,"column":3}},{"generated":{"line":42,"column":3},"source":"../src/Tooltip/Tooltip.js","original":{"line":5,"column":15}},{"name":"mounted","generated":{"line":43,"column":0},"source":"../src/Tooltip/Tooltip.js","original":{"line":29,"column":2}},{"generated":{"line":43,"column":9},"source":"../src/Tooltip/Tooltip.js","original":{"line":5,"column":15}},{"generated":{"line":43,"column":30},"source":"../src/Tooltip/Tooltip.js","original":{"line":29,"column":13}},{"generated":{"line":44,"column":0},"source":"../src/Tooltip/Tooltip.js","original":{"line":30,"column":4}},{"name":"trigger","generated":{"line":44,"column":9},"source":"../src/Tooltip/Tooltip.js","original":{"line":30,"column":9}},{"generated":{"line":44,"column":16},"source":"../src/Tooltip/Tooltip.js","original":{"line":30,"column":4}},{"generated":{"line":44,"column":19},"source":"../src/Tooltip/Tooltip.js","original":{"line":30,"column":19}},{"name":"$el","generated":{"line":44,"column":24},"source":"../src/Tooltip/Tooltip.js","original":{"line":30,"column":24}},{"generated":{"line":44,"column":27},"source":"../src/Tooltip/Tooltip.js","original":{"line":30,"column":4}},{"generated":{"line":45,"column":0},"source":"../src/Tooltip/Tooltip.js","original":{"line":31,"column":3}},{"generated":{"line":45,"column":3},"source":"../src/Tooltip/Tooltip.js","original":{"line":5,"column":15}},{"name":"methods","generated":{"line":47,"column":0},"source":"../src/Tooltip/Tooltip.js","original":{"line":32,"column":2}},{"generated":{"line":47,"column":11},"source":"../src/Tooltip/Tooltip.js","original":{"line":32,"column":11}},{"name":"addEventHandle","generated":{"line":48,"column":0},"source":"../src/Tooltip/Tooltip.js","original":{"line":33,"column":4}},{"generated":{"line":48,"column":18},"source":"../src/Tooltip/Tooltip.js","original":{"line":32,"column":11}},{"name":"old","generated":{"line":48,"column":44},"source":"../src/Tooltip/Tooltip.js","original":{"line":33,"column":20}},{"generated":{"line":48,"column":47},"source":"../src/Tooltip/Tooltip.js","original":{"line":32,"column":11}},{"name":"fn","generated":{"line":48,"column":49},"source":"../src/Tooltip/Tooltip.js","original":{"line":33,"column":25}},{"generated":{"line":48,"column":51},"source":"../src/Tooltip/Tooltip.js","original":{"line":32,"column":11}},{"generated":{"line":48,"column":53},"source":"../src/Tooltip/Tooltip.js","original":{"line":33,"column":29}},{"generated":{"line":49,"column":0},"source":"../src/Tooltip/Tooltip.js","original":{"line":34,"column":6}},{"generated":{"line":49,"column":10},"source":"../src/Tooltip/Tooltip.js","original":{"line":34,"column":10}},{"name":"old","generated":{"line":49,"column":11},"source":"../src/Tooltip/Tooltip.js","original":{"line":34,"column":11}},{"generated":{"line":49,"column":14},"source":"../src/Tooltip/Tooltip.js","original":{"line":34,"column":6}},{"generated":{"line":49,"column":16},"source":"../src/Tooltip/Tooltip.js","original":{"line":34,"column":16}},{"generated":{"line":50,"column":0},"source":"../src/Tooltip/Tooltip.js","original":{"line":35,"column":8}},{"name":"fn","generated":{"line":50,"column":15},"source":"../src/Tooltip/Tooltip.js","original":{"line":35,"column":15}},{"generated":{"line":50,"column":17},"source":"../src/Tooltip/Tooltip.js","original":{"line":35,"column":8}},{"generated":{"line":51,"column":0},"source":"../src/Tooltip/Tooltip.js","original":{"line":36,"column":7}},{"generated":{"line":51,"column":7},"source":"../src/Tooltip/Tooltip.js","original":{"line":34,"column":6}},{"generated":{"line":51,"column":13},"source":"../src/Tooltip/Tooltip.js","original":{"line":36,"column":13}},{"name":"Array","generated":{"line":51,"column":17},"source":"../src/Tooltip/Tooltip.js","original":{"line":36,"column":17}},{"name":"isArray","generated":{"line":51,"column":23},"source":"../src/Tooltip/Tooltip.js","original":{"line":36,"column":23}},{"generated":{"line":51,"column":30},"source":"../src/Tooltip/Tooltip.js","original":{"line":36,"column":17}},{"name":"old","generated":{"line":51,"column":31},"source":"../src/Tooltip/Tooltip.js","original":{"line":36,"column":31}},{"generated":{"line":51,"column":34},"source":"../src/Tooltip/Tooltip.js","original":{"line":36,"column":17}},{"generated":{"line":51,"column":35},"source":"../src/Tooltip/Tooltip.js","original":{"line":36,"column":13}},{"generated":{"line":51,"column":37},"source":"../src/Tooltip/Tooltip.js","original":{"line":36,"column":37}},{"generated":{"line":52,"column":0},"source":"../src/Tooltip/Tooltip.js","original":{"line":37,"column":8}},{"name":"old","generated":{"line":52,"column":15},"source":"../src/Tooltip/Tooltip.js","original":{"line":37,"column":15}},{"name":"indexOf","generated":{"line":52,"column":19},"source":"../src/Tooltip/Tooltip.js","original":{"line":37,"column":19}},{"generated":{"line":52,"column":26},"source":"../src/Tooltip/Tooltip.js","original":{"line":37,"column":15}},{"name":"fn","generated":{"line":52,"column":27},"source":"../src/Tooltip/Tooltip.js","original":{"line":37,"column":27}},{"generated":{"line":52,"column":29},"source":"../src/Tooltip/Tooltip.js","original":{"line":37,"column":15}},{"generated":{"line":52,"column":33},"source":"../src/Tooltip/Tooltip.js","original":{"line":37,"column":33}},{"generated":{"line":52,"column":34},"source":"../src/Tooltip/Tooltip.js","original":{"line":37,"column":34}},{"generated":{"line":52,"column":35},"source":"../src/Tooltip/Tooltip.js","original":{"line":37,"column":15}},{"name":"old","generated":{"line":52,"column":38},"source":"../src/Tooltip/Tooltip.js","original":{"line":37,"column":38}},{"generated":{"line":52,"column":41},"source":"../src/Tooltip/Tooltip.js","original":{"line":37,"column":15}},{"name":"old","generated":{"line":52,"column":44},"source":"../src/Tooltip/Tooltip.js","original":{"line":37,"column":44}},{"name":"concat","generated":{"line":52,"column":48},"source":"../src/Tooltip/Tooltip.js","original":{"line":37,"column":48}},{"generated":{"line":52,"column":54},"source":"../src/Tooltip/Tooltip.js","original":{"line":37,"column":44}},{"name":"fn","generated":{"line":52,"column":55},"source":"../src/Tooltip/Tooltip.js","original":{"line":37,"column":55}},{"generated":{"line":52,"column":57},"source":"../src/Tooltip/Tooltip.js","original":{"line":37,"column":44}},{"generated":{"line":52,"column":58},"source":"../src/Tooltip/Tooltip.js","original":{"line":37,"column":8}},{"generated":{"line":53,"column":0},"source":"../src/Tooltip/Tooltip.js","original":{"line":38,"column":7}},{"generated":{"line":53,"column":7},"source":"../src/Tooltip/Tooltip.js","original":{"line":36,"column":13}},{"generated":{"line":53,"column":13},"source":"../src/Tooltip/Tooltip.js","original":{"line":38,"column":13}},{"generated":{"line":54,"column":0},"source":"../src/Tooltip/Tooltip.js","original":{"line":39,"column":8}},{"name":"old","generated":{"line":54,"column":15},"source":"../src/Tooltip/Tooltip.js","original":{"line":39,"column":15}},{"name":"fn","generated":{"line":54,"column":23},"source":"../src/Tooltip/Tooltip.js","original":{"line":39,"column":23}},{"generated":{"line":54,"column":25},"source":"../src/Tooltip/Tooltip.js","original":{"line":39,"column":15}},{"name":"old","generated":{"line":54,"column":28},"source":"../src/Tooltip/Tooltip.js","original":{"line":39,"column":28}},{"generated":{"line":54,"column":31},"source":"../src/Tooltip/Tooltip.js","original":{"line":39,"column":15}},{"generated":{"line":54,"column":34},"source":"../src/Tooltip/Tooltip.js","original":{"line":39,"column":34}},{"name":"old","generated":{"line":54,"column":35},"source":"../src/Tooltip/Tooltip.js","original":{"line":39,"column":35}},{"generated":{"line":54,"column":38},"source":"../src/Tooltip/Tooltip.js","original":{"line":39,"column":34}},{"name":"fn","generated":{"line":54,"column":40},"source":"../src/Tooltip/Tooltip.js","original":{"line":39,"column":40}},{"generated":{"line":54,"column":42},"source":"../src/Tooltip/Tooltip.js","original":{"line":39,"column":34}},{"generated":{"line":54,"column":43},"source":"../src/Tooltip/Tooltip.js","original":{"line":39,"column":8}},{"generated":{"line":55,"column":0},"source":"../src/Tooltip/Tooltip.js","original":{"line":40,"column":7}},{"generated":{"line":56,"column":0},"source":"../src/Tooltip/Tooltip.js","original":{"line":41,"column":5}},{"generated":{"line":56,"column":5},"source":"../src/Tooltip/Tooltip.js","original":{"line":32,"column":11}},{"name":"show","generated":{"line":57,"column":0},"source":"../src/Tooltip/Tooltip.js","original":{"line":42,"column":4}},{"generated":{"line":57,"column":8},"source":"../src/Tooltip/Tooltip.js","original":{"line":32,"column":11}},{"generated":{"line":57,"column":26},"source":"../src/Tooltip/Tooltip.js","original":{"line":42,"column":12}},{"generated":{"line":58,"column":0},"source":"../src/Tooltip/Tooltip.js","original":{"line":43,"column":6}},{"generated":{"line":58,"column":10},"source":"../src/Tooltip/Tooltip.js","original":{"line":43,"column":10}},{"name":"timer","generated":{"line":58,"column":15},"source":"../src/Tooltip/Tooltip.js","original":{"line":43,"column":15}},{"generated":{"line":58,"column":20},"source":"../src/Tooltip/Tooltip.js","original":{"line":43,"column":6}},{"name":"clearTimeout","generated":{"line":58,"column":22},"source":"../src/Tooltip/Tooltip.js","original":{"line":43,"column":22}},{"generated":{"line":58,"column":35},"source":"../src/Tooltip/Tooltip.js","original":{"line":43,"column":35}},{"name":"timer","generated":{"line":58,"column":40},"source":"../src/Tooltip/Tooltip.js","original":{"line":43,"column":40}},{"generated":{"line":58,"column":45},"source":"../src/Tooltip/Tooltip.js","original":{"line":43,"column":22}},{"generated":{"line":59,"column":0},"source":"../src/Tooltip/Tooltip.js","original":{"line":44,"column":6}},{"name":"active","generated":{"line":59,"column":11},"source":"../src/Tooltip/Tooltip.js","original":{"line":44,"column":11}},{"generated":{"line":59,"column":17},"source":"../src/Tooltip/Tooltip.js","original":{"line":44,"column":6}},{"generated":{"line":59,"column":20},"source":"../src/Tooltip/Tooltip.js","original":{"line":44,"column":20}},{"generated":{"line":59,"column":24},"source":"../src/Tooltip/Tooltip.js","original":{"line":44,"column":6}},{"generated":{"line":60,"column":0},"source":"../src/Tooltip/Tooltip.js","original":{"line":45,"column":5}},{"generated":{"line":60,"column":5},"source":"../src/Tooltip/Tooltip.js","original":{"line":32,"column":11}},{"name":"hide","generated":{"line":61,"column":0},"source":"../src/Tooltip/Tooltip.js","original":{"line":46,"column":4}},{"generated":{"line":61,"column":8},"source":"../src/Tooltip/Tooltip.js","original":{"line":32,"column":11}},{"generated":{"line":61,"column":26},"source":"../src/Tooltip/Tooltip.js","original":{"line":46,"column":12}},{"generated":{"line":62,"column":0},"source":"../src/Tooltip/Tooltip.js","original":{"line":46,"column":12}},{"generated":{"line":64,"column":0},"source":"../src/Tooltip/Tooltip.js","original":{"line":47,"column":6}},{"generated":{"line":64,"column":10},"source":"../src/Tooltip/Tooltip.js","original":{"line":47,"column":10}},{"name":"timer","generated":{"line":64,"column":15},"source":"../src/Tooltip/Tooltip.js","original":{"line":47,"column":15}},{"generated":{"line":64,"column":20},"source":"../src/Tooltip/Tooltip.js","original":{"line":47,"column":6}},{"name":"clearTimeout","generated":{"line":64,"column":22},"source":"../src/Tooltip/Tooltip.js","original":{"line":47,"column":22}},{"generated":{"line":64,"column":35},"source":"../src/Tooltip/Tooltip.js","original":{"line":47,"column":35}},{"name":"timer","generated":{"line":64,"column":40},"source":"../src/Tooltip/Tooltip.js","original":{"line":47,"column":40}},{"generated":{"line":64,"column":45},"source":"../src/Tooltip/Tooltip.js","original":{"line":47,"column":22}},{"generated":{"line":65,"column":0},"source":"../src/Tooltip/Tooltip.js","original":{"line":48,"column":6}},{"name":"timer","generated":{"line":65,"column":11},"source":"../src/Tooltip/Tooltip.js","original":{"line":48,"column":11}},{"generated":{"line":65,"column":16},"source":"../src/Tooltip/Tooltip.js","original":{"line":48,"column":6}},{"name":"setTimeout","generated":{"line":65,"column":19},"source":"../src/Tooltip/Tooltip.js","original":{"line":48,"column":19}},{"generated":{"line":65,"column":30},"source":"../src/Tooltip/Tooltip.js","original":{"line":48,"column":30}},{"generated":{"line":65,"column":42},"source":"../src/Tooltip/Tooltip.js","original":{"line":48,"column":36}},{"generated":{"line":66,"column":0},"source":"../src/Tooltip/Tooltip.js","original":{"line":49,"column":8}},{"name":"active","generated":{"line":66,"column":14},"source":"../src/Tooltip/Tooltip.js","original":{"line":49,"column":13}},{"generated":{"line":66,"column":20},"source":"../src/Tooltip/Tooltip.js","original":{"line":49,"column":8}},{"generated":{"line":66,"column":23},"source":"../src/Tooltip/Tooltip.js","original":{"line":49,"column":22}},{"generated":{"line":66,"column":28},"source":"../src/Tooltip/Tooltip.js","original":{"line":49,"column":8}},{"generated":{"line":67,"column":0},"source":"../src/Tooltip/Tooltip.js","original":{"line":50,"column":7}},{"generated":{"line":67,"column":7},"source":"../src/Tooltip/Tooltip.js","original":{"line":48,"column":19}},{"generated":{"line":67,"column":9},"source":"../src/Tooltip/Tooltip.js","original":{"line":50,"column":9}},{"generated":{"line":67,"column":12},"source":"../src/Tooltip/Tooltip.js","original":{"line":48,"column":19}},{"generated":{"line":67,"column":13},"source":"../src/Tooltip/Tooltip.js","original":{"line":48,"column":6}},{"generated":{"line":68,"column":0},"source":"../src/Tooltip/Tooltip.js","original":{"line":51,"column":5}},{"generated":{"line":69,"column":0},"source":"../src/Tooltip/Tooltip.js","original":{"line":32,"column":11}},{"generated":{"line":69,"column":3},"source":"../src/Tooltip/Tooltip.js","original":{"line":5,"column":15}},{"name":"watch","generated":{"line":70,"column":0},"source":"../src/Tooltip/Tooltip.js","original":{"line":53,"column":2}},{"generated":{"line":70,"column":9},"source":"../src/Tooltip/Tooltip.js","original":{"line":53,"column":9}},{"name":"active","generated":{"line":71,"column":0},"source":"../src/Tooltip/Tooltip.js","original":{"line":54,"column":4}},{"generated":{"line":71,"column":10},"source":"../src/Tooltip/Tooltip.js","original":{"line":53,"column":9}},{"name":"val","generated":{"line":71,"column":28},"source":"../src/Tooltip/Tooltip.js","original":{"line":54,"column":12}},{"generated":{"line":71,"column":31},"source":"../src/Tooltip/Tooltip.js","original":{"line":53,"column":9}},{"generated":{"line":71,"column":33},"source":"../src/Tooltip/Tooltip.js","original":{"line":54,"column":17}},{"generated":{"line":72,"column":0},"source":"../src/Tooltip/Tooltip.js","original":{"line":55,"column":6}},{"name":"$emit","generated":{"line":72,"column":11},"source":"../src/Tooltip/Tooltip.js","original":{"line":55,"column":11}},{"generated":{"line":72,"column":16},"source":"../src/Tooltip/Tooltip.js","original":{"line":55,"column":6}},{"generated":{"line":72,"column":17},"source":"../src/Tooltip/Tooltip.js","original":{"line":55,"column":17}},{"generated":{"line":72,"column":30},"source":"../src/Tooltip/Tooltip.js","original":{"line":55,"column":6}},{"name":"val","generated":{"line":72,"column":32},"source":"../src/Tooltip/Tooltip.js","original":{"line":55,"column":32}},{"generated":{"line":72,"column":35},"source":"../src/Tooltip/Tooltip.js","original":{"line":55,"column":6}},{"generated":{"line":73,"column":0},"source":"../src/Tooltip/Tooltip.js","original":{"line":56,"column":5}},{"generated":{"line":73,"column":5},"source":"../src/Tooltip/Tooltip.js","original":{"line":53,"column":9}},{"name":"open","generated":{"line":74,"column":0},"source":"../src/Tooltip/Tooltip.js","original":{"line":57,"column":4}},{"generated":{"line":74,"column":8},"source":"../src/Tooltip/Tooltip.js","original":{"line":53,"column":9}},{"name":"val","generated":{"line":74,"column":24},"source":"../src/Tooltip/Tooltip.js","original":{"line":57,"column":10}},{"generated":{"line":74,"column":27},"source":"../src/Tooltip/Tooltip.js","original":{"line":53,"column":9}},{"generated":{"line":74,"column":29},"source":"../src/Tooltip/Tooltip.js","original":{"line":57,"column":15}},{"generated":{"line":75,"column":0},"source":"../src/Tooltip/Tooltip.js","original":{"line":58,"column":6}},{"name":"active","generated":{"line":75,"column":11},"source":"../src/Tooltip/Tooltip.js","original":{"line":58,"column":11}},{"generated":{"line":75,"column":17},"source":"../src/Tooltip/Tooltip.js","original":{"line":58,"column":6}},{"name":"val","generated":{"line":75,"column":20},"source":"../src/Tooltip/Tooltip.js","original":{"line":58,"column":20}},{"generated":{"line":75,"column":23},"source":"../src/Tooltip/Tooltip.js","original":{"line":58,"column":6}},{"generated":{"line":76,"column":0},"source":"../src/Tooltip/Tooltip.js","original":{"line":59,"column":5}},{"generated":{"line":77,"column":0},"source":"../src/Tooltip/Tooltip.js","original":{"line":53,"column":9}},{"generated":{"line":77,"column":3},"source":"../src/Tooltip/Tooltip.js","original":{"line":5,"column":15}},{"name":"render","generated":{"line":78,"column":0},"source":"../src/Tooltip/Tooltip.js","original":{"line":61,"column":2}},{"generated":{"line":78,"column":8},"source":"../src/Tooltip/Tooltip.js","original":{"line":5,"column":15}},{"name":"h","generated":{"line":78,"column":26},"source":"../src/Tooltip/Tooltip.js","original":{"line":61,"column":10}},{"generated":{"line":78,"column":27},"source":"../src/Tooltip/Tooltip.js","original":{"line":5,"column":15}},{"generated":{"line":78,"column":29},"source":"../src/Tooltip/Tooltip.js","original":{"line":61,"column":13}},{"generated":{"line":79,"column":0},"source":"../src/Tooltip/Tooltip.js","original":{"line":61,"column":13}},{"generated":{"line":81,"column":0},"source":"../src/Tooltip/Tooltip.js","original":{"line":62,"column":4}},{"name":"content","generated":{"line":81,"column":8},"source":"../src/Tooltip/Tooltip.js","original":{"line":62,"column":10}},{"generated":{"line":81,"column":18},"source":"../src/Tooltip/Tooltip.js","original":{"line":62,"column":20}},{"generated":{"line":81,"column":19},"source":"../src/Tooltip/Tooltip.js","original":{"line":62,"column":21}},{"name":"$slots","generated":{"line":81,"column":24},"source":"../src/Tooltip/Tooltip.js","original":{"line":62,"column":26}},{"generated":{"line":81,"column":30},"source":"../src/Tooltip/Tooltip.js","original":{"line":62,"column":21}},{"name":"content","generated":{"line":81,"column":31},"source":"../src/Tooltip/Tooltip.js","original":{"line":62,"column":33}},{"generated":{"line":81,"column":38},"source":"../src/Tooltip/Tooltip.js","original":{"line":62,"column":21}},{"generated":{"line":81,"column":42},"source":"../src/Tooltip/Tooltip.js","original":{"line":62,"column":44}},{"name":"$slots","generated":{"line":81,"column":47},"source":"../src/Tooltip/Tooltip.js","original":{"line":62,"column":49}},{"generated":{"line":81,"column":53},"source":"../src/Tooltip/Tooltip.js","original":{"line":62,"column":44}},{"name":"content","generated":{"line":81,"column":54},"source":"../src/Tooltip/Tooltip.js","original":{"line":62,"column":56}},{"generated":{"line":81,"column":61},"source":"../src/Tooltip/Tooltip.js","original":{"line":62,"column":44}},{"name":"length","generated":{"line":81,"column":62},"source":"../src/Tooltip/Tooltip.js","original":{"line":62,"column":64}},{"generated":{"line":81,"column":68},"source":"../src/Tooltip/Tooltip.js","original":{"line":62,"column":44}},{"generated":{"line":81,"column":71},"source":"../src/Tooltip/Tooltip.js","original":{"line":62,"column":73}},{"generated":{"line":81,"column":72},"source":"../src/Tooltip/Tooltip.js","original":{"line":62,"column":21}},{"generated":{"line":81,"column":75},"source":"../src/Tooltip/Tooltip.js","original":{"line":62,"column":77}},{"name":"$slots","generated":{"line":81,"column":80},"source":"../src/Tooltip/Tooltip.js","original":{"line":62,"column":82}},{"generated":{"line":81,"column":86},"source":"../src/Tooltip/Tooltip.js","original":{"line":62,"column":77}},{"name":"content","generated":{"line":81,"column":87},"source":"../src/Tooltip/Tooltip.js","original":{"line":62,"column":89}},{"generated":{"line":81,"column":94},"source":"../src/Tooltip/Tooltip.js","original":{"line":62,"column":21}},{"generated":{"line":81,"column":97},"source":"../src/Tooltip/Tooltip.js","original":{"line":62,"column":99}},{"name":"content","generated":{"line":81,"column":102},"source":"../src/Tooltip/Tooltip.js","original":{"line":62,"column":104}},{"generated":{"line":81,"column":109},"source":"../src/Tooltip/Tooltip.js","original":{"line":62,"column":20}},{"generated":{"line":81,"column":114},"source":"../src/Tooltip/Tooltip.js","original":{"line":62,"column":116}},{"generated":{"line":81,"column":116},"source":"../src/Tooltip/Tooltip.js","original":{"line":62,"column":4}},{"generated":{"line":82,"column":0},"source":"../src/Tooltip/Tooltip.js","original":{"line":63,"column":4}},{"name":"tooltipVM","generated":{"line":82,"column":9},"source":"../src/Tooltip/Tooltip.js","original":{"line":63,"column":9}},{"generated":{"line":82,"column":18},"source":"../src/Tooltip/Tooltip.js","original":{"line":63,"column":4}},{"name":"node","generated":{"line":82,"column":19},"source":"../src/Tooltip/Tooltip.js","original":{"line":63,"column":19}},{"generated":{"line":82,"column":23},"source":"../src/Tooltip/Tooltip.js","original":{"line":63,"column":4}},{"name":"h","generated":{"line":82,"column":26},"source":"../src/Tooltip/Tooltip.js","original":{"line":63,"column":26}},{"generated":{"line":82,"column":54},"source":"../src/Tooltip/Tooltip.js","original":{"line":63,"column":44}},{"name":"class","generated":{"line":83,"column":0},"source":"../src/Tooltip/Tooltip.js","original":{"line":64,"column":6}},{"generated":{"line":83,"column":13},"source":"../src/Tooltip/Tooltip.js","original":{"line":64,"column":13}},{"name":"tooltipClass","generated":{"line":83,"column":18},"source":"../src/Tooltip/Tooltip.js","original":{"line":64,"column":18}},{"generated":{"line":83,"column":30},"source":"../src/Tooltip/Tooltip.js","original":{"line":63,"column":44}},{"name":"props","generated":{"line":84,"column":0},"source":"../src/Tooltip/Tooltip.js","original":{"line":65,"column":6}},{"generated":{"line":84,"column":13},"source":"../src/Tooltip/Tooltip.js","original":{"line":65,"column":13}},{"name":"placement","generated":{"line":85,"column":0},"source":"../src/Tooltip/Tooltip.js","original":{"line":66,"column":8}},{"generated":{"line":85,"column":19},"source":"../src/Tooltip/Tooltip.js","original":{"line":66,"column":19}},{"name":"placement","generated":{"line":85,"column":24},"source":"../src/Tooltip/Tooltip.js","original":{"line":66,"column":24}},{"generated":{"line":85,"column":33},"source":"../src/Tooltip/Tooltip.js","original":{"line":65,"column":13}},{"name":"open","generated":{"line":86,"column":0},"source":"../src/Tooltip/Tooltip.js","original":{"line":67,"column":8}},{"generated":{"line":86,"column":14},"source":"../src/Tooltip/Tooltip.js","original":{"line":67,"column":14}},{"name":"active","generated":{"line":86,"column":19},"source":"../src/Tooltip/Tooltip.js","original":{"line":67,"column":19}},{"generated":{"line":86,"column":25},"source":"../src/Tooltip/Tooltip.js","original":{"line":65,"column":13}},{"name":"trigger","generated":{"line":87,"column":0},"source":"../src/Tooltip/Tooltip.js","original":{"line":68,"column":8}},{"generated":{"line":87,"column":17},"source":"../src/Tooltip/Tooltip.js","original":{"line":68,"column":17}},{"name":"trigger","generated":{"line":87,"column":22},"source":"../src/Tooltip/Tooltip.js","original":{"line":68,"column":22}},{"generated":{"line":88,"column":0},"source":"../src/Tooltip/Tooltip.js","original":{"line":65,"column":13}},{"generated":{"line":88,"column":7},"source":"../src/Tooltip/Tooltip.js","original":{"line":63,"column":44}},{"name":"nativeOn","generated":{"line":89,"column":0},"source":"../src/Tooltip/Tooltip.js","original":{"line":70,"column":6}},{"generated":{"line":89,"column":16},"source":"../src/Tooltip/Tooltip.js","original":{"line":70,"column":16}},{"name":"mouseenter","generated":{"line":90,"column":0},"source":"../src/Tooltip/Tooltip.js","original":{"line":71,"column":8}},{"generated":{"line":90,"column":20},"source":"../src/Tooltip/Tooltip.js","original":{"line":71,"column":20}},{"generated":{"line":91,"column":0},"source":"../src/Tooltip/Tooltip.js","original":{"line":71,"column":20}},{"generated":{"line":91,"column":17},"source":"../src/Tooltip/Tooltip.js","original":{"line":71,"column":26}},{"name":"show","generated":{"line":91,"column":24},"source":"../src/Tooltip/Tooltip.js","original":{"line":71,"column":31}},{"generated":{"line":91,"column":28},"source":"../src/Tooltip/Tooltip.js","original":{"line":71,"column":26}},{"generated":{"line":91,"column":30},"source":"../src/Tooltip/Tooltip.js","original":{"line":71,"column":20}},{"generated":{"line":92,"column":0},"source":"../src/Tooltip/Tooltip.js","original":{"line":71,"column":20}},{"generated":{"line":92,"column":9},"source":"../src/Tooltip/Tooltip.js","original":{"line":70,"column":16}},{"name":"mouseleave","generated":{"line":93,"column":0},"source":"../src/Tooltip/Tooltip.js","original":{"line":72,"column":8}},{"generated":{"line":93,"column":20},"source":"../src/Tooltip/Tooltip.js","original":{"line":72,"column":20}},{"generated":{"line":94,"column":0},"source":"../src/Tooltip/Tooltip.js","original":{"line":72,"column":20}},{"generated":{"line":94,"column":17},"source":"../src/Tooltip/Tooltip.js","original":{"line":72,"column":26}},{"name":"hide","generated":{"line":94,"column":24},"source":"../src/Tooltip/Tooltip.js","original":{"line":72,"column":31}},{"generated":{"line":94,"column":28},"source":"../src/Tooltip/Tooltip.js","original":{"line":72,"column":26}},{"generated":{"line":94,"column":30},"source":"../src/Tooltip/Tooltip.js","original":{"line":72,"column":20}},{"generated":{"line":95,"column":0},"source":"../src/Tooltip/Tooltip.js","original":{"line":72,"column":20}},{"generated":{"line":96,"column":0},"source":"../src/Tooltip/Tooltip.js","original":{"line":70,"column":16}},{"generated":{"line":97,"column":0},"source":"../src/Tooltip/Tooltip.js","original":{"line":63,"column":44}},{"generated":{"line":97,"column":5},"source":"../src/Tooltip/Tooltip.js","original":{"line":63,"column":26}},{"name":"content","generated":{"line":97,"column":7},"source":"../src/Tooltip/Tooltip.js","original":{"line":74,"column":7}},{"generated":{"line":97,"column":14},"source":"../src/Tooltip/Tooltip.js","original":{"line":63,"column":26}},{"generated":{"line":97,"column":15},"source":"../src/Tooltip/Tooltip.js","original":{"line":63,"column":4}},{"generated":{"line":99,"column":0},"source":"../src/Tooltip/Tooltip.js","original":{"line":76,"column":4}},{"name":"vnode","generated":{"line":99,"column":8},"source":"../src/Tooltip/Tooltip.js","original":{"line":76,"column":10}},{"generated":{"line":99,"column":16},"source":"../src/Tooltip/Tooltip.js","original":{"line":76,"column":18}},{"generated":{"line":99,"column":51},"source":"../src/Tooltip/Tooltip.js","original":{"line":76,"column":41}},{"name":"$slots","generated":{"line":99,"column":56},"source":"../src/Tooltip/Tooltip.js","original":{"line":76,"column":46}},{"generated":{"line":99,"column":62},"source":"../src/Tooltip/Tooltip.js","original":{"line":76,"column":41}},{"name":"default","generated":{"line":99,"column":63},"source":"../src/Tooltip/Tooltip.js","original":{"line":76,"column":53}},{"generated":{"line":99,"column":70},"source":"../src/Tooltip/Tooltip.js","original":{"line":76,"column":18}},{"generated":{"line":99,"column":71},"source":"../src/Tooltip/Tooltip.js","original":{"line":76,"column":4}},{"generated":{"line":100,"column":0},"source":"../src/Tooltip/Tooltip.js","original":{"line":77,"column":4}},{"generated":{"line":100,"column":8},"source":"../src/Tooltip/Tooltip.js","original":{"line":77,"column":8}},{"name":"vnode","generated":{"line":100,"column":9},"source":"../src/Tooltip/Tooltip.js","original":{"line":77,"column":9}},{"generated":{"line":100,"column":14},"source":"../src/Tooltip/Tooltip.js","original":{"line":77,"column":4}},{"generated":{"line":100,"column":16},"source":"../src/Tooltip/Tooltip.js","original":{"line":77,"column":16}},{"name":"vnode","generated":{"line":100,"column":23},"source":"../src/Tooltip/Tooltip.js","original":{"line":77,"column":23}},{"generated":{"line":100,"column":28},"source":"../src/Tooltip/Tooltip.js","original":{"line":77,"column":16}},{"generated":{"line":102,"column":0},"source":"../src/Tooltip/Tooltip.js","original":{"line":79,"column":4}},{"name":"on","generated":{"line":102,"column":8},"source":"../src/Tooltip/Tooltip.js","original":{"line":79,"column":10}},{"name":"vnode","generated":{"line":102,"column":13},"source":"../src/Tooltip/Tooltip.js","original":{"line":79,"column":15}},{"name":"data","generated":{"line":102,"column":19},"source":"../src/Tooltip/Tooltip.js","original":{"line":79,"column":21}},{"generated":{"line":102,"column":23},"source":"../src/Tooltip/Tooltip.js","original":{"line":79,"column":15}},{"name":"on","generated":{"line":102,"column":24},"source":"../src/Tooltip/Tooltip.js","original":{"line":79,"column":26}},{"generated":{"line":102,"column":26},"source":"../src/Tooltip/Tooltip.js","original":{"line":79,"column":15}},{"name":"vnode","generated":{"line":102,"column":29},"source":"../src/Tooltip/Tooltip.js","original":{"line":79,"column":31}},{"name":"data","generated":{"line":102,"column":35},"source":"../src/Tooltip/Tooltip.js","original":{"line":79,"column":37}},{"generated":{"line":102,"column":39},"source":"../src/Tooltip/Tooltip.js","original":{"line":79,"column":31}},{"name":"on","generated":{"line":102,"column":40},"source":"../src/Tooltip/Tooltip.js","original":{"line":79,"column":42}},{"generated":{"line":102,"column":42},"source":"../src/Tooltip/Tooltip.js","original":{"line":79,"column":31}},{"generated":{"line":102,"column":46},"source":"../src/Tooltip/Tooltip.js","original":{"line":79,"column":48}},{"generated":{"line":102,"column":48},"source":"../src/Tooltip/Tooltip.js","original":{"line":79,"column":4}},{"generated":{"line":103,"column":0},"source":"../src/Tooltip/Tooltip.js","original":{"line":80,"column":4}},{"name":"nativeOn","generated":{"line":103,"column":8},"source":"../src/Tooltip/Tooltip.js","original":{"line":80,"column":10}},{"name":"vnode","generated":{"line":103,"column":19},"source":"../src/Tooltip/Tooltip.js","original":{"line":80,"column":21}},{"name":"data","generated":{"line":103,"column":25},"source":"../src/Tooltip/Tooltip.js","original":{"line":80,"column":27}},{"generated":{"line":103,"column":29},"source":"../src/Tooltip/Tooltip.js","original":{"line":80,"column":21}},{"name":"nativeOn","generated":{"line":103,"column":30},"source":"../src/Tooltip/Tooltip.js","original":{"line":80,"column":32}},{"generated":{"line":103,"column":38},"source":"../src/Tooltip/Tooltip.js","original":{"line":80,"column":21}},{"name":"vnode","generated":{"line":103,"column":41},"source":"../src/Tooltip/Tooltip.js","original":{"line":80,"column":43}},{"name":"data","generated":{"line":103,"column":47},"source":"../src/Tooltip/Tooltip.js","original":{"line":80,"column":49}},{"generated":{"line":103,"column":51},"source":"../src/Tooltip/Tooltip.js","original":{"line":80,"column":43}},{"name":"nativeOn","generated":{"line":103,"column":52},"source":"../src/Tooltip/Tooltip.js","original":{"line":80,"column":54}},{"generated":{"line":103,"column":60},"source":"../src/Tooltip/Tooltip.js","original":{"line":80,"column":43}},{"generated":{"line":103,"column":64},"source":"../src/Tooltip/Tooltip.js","original":{"line":80,"column":66}},{"generated":{"line":103,"column":66},"source":"../src/Tooltip/Tooltip.js","original":{"line":80,"column":4}},{"name":"nativeOn","generated":{"line":104,"column":0},"source":"../src/Tooltip/Tooltip.js","original":{"line":81,"column":4}},{"name":"mouseenter","generated":{"line":104,"column":13},"source":"../src/Tooltip/Tooltip.js","original":{"line":81,"column":13}},{"generated":{"line":104,"column":23},"source":"../src/Tooltip/Tooltip.js","original":{"line":81,"column":4}},{"name":"on","generated":{"line":104,"column":26},"source":"../src/Tooltip/Tooltip.js","original":{"line":81,"column":26}},{"name":"mouseenter","generated":{"line":104,"column":29},"source":"../src/Tooltip/Tooltip.js","original":{"line":81,"column":29}},{"generated":{"line":104,"column":39},"source":"../src/Tooltip/Tooltip.js","original":{"line":81,"column":26}},{"generated":{"line":104,"column":42},"source":"../src/Tooltip/Tooltip.js","original":{"line":81,"column":42}},{"name":"addEventHandle","generated":{"line":104,"column":47},"source":"../src/Tooltip/Tooltip.js","original":{"line":81,"column":47}},{"generated":{"line":104,"column":61},"source":"../src/Tooltip/Tooltip.js","original":{"line":81,"column":42}},{"name":"on","generated":{"line":104,"column":62},"source":"../src/Tooltip/Tooltip.js","original":{"line":81,"column":62}},{"name":"mouseenter","generated":{"line":104,"column":65},"source":"../src/Tooltip/Tooltip.js","original":{"line":81,"column":65}},{"generated":{"line":104,"column":75},"source":"../src/Tooltip/Tooltip.js","original":{"line":81,"column":42}},{"generated":{"line":104,"column":77},"source":"../src/Tooltip/Tooltip.js","original":{"line":81,"column":77}},{"name":"show","generated":{"line":104,"column":82},"source":"../src/Tooltip/Tooltip.js","original":{"line":81,"column":82}},{"generated":{"line":104,"column":86},"source":"../src/Tooltip/Tooltip.js","original":{"line":81,"column":42}},{"generated":{"line":104,"column":87},"source":"../src/Tooltip/Tooltip.js","original":{"line":81,"column":4}},{"name":"nativeOn","generated":{"line":105,"column":0},"source":"../src/Tooltip/Tooltip.js","original":{"line":82,"column":4}},{"name":"mouseleave","generated":{"line":105,"column":13},"source":"../src/Tooltip/Tooltip.js","original":{"line":82,"column":13}},{"generated":{"line":105,"column":23},"source":"../src/Tooltip/Tooltip.js","original":{"line":82,"column":4}},{"name":"on","generated":{"line":105,"column":26},"source":"../src/Tooltip/Tooltip.js","original":{"line":82,"column":26}},{"name":"mouseleave","generated":{"line":105,"column":29},"source":"../src/Tooltip/Tooltip.js","original":{"line":82,"column":29}},{"generated":{"line":105,"column":39},"source":"../src/Tooltip/Tooltip.js","original":{"line":82,"column":26}},{"generated":{"line":105,"column":42},"source":"../src/Tooltip/Tooltip.js","original":{"line":82,"column":42}},{"name":"addEventHandle","generated":{"line":105,"column":47},"source":"../src/Tooltip/Tooltip.js","original":{"line":82,"column":47}},{"generated":{"line":105,"column":61},"source":"../src/Tooltip/Tooltip.js","original":{"line":82,"column":42}},{"name":"on","generated":{"line":105,"column":62},"source":"../src/Tooltip/Tooltip.js","original":{"line":82,"column":62}},{"name":"mouseleave","generated":{"line":105,"column":65},"source":"../src/Tooltip/Tooltip.js","original":{"line":82,"column":65}},{"generated":{"line":105,"column":75},"source":"../src/Tooltip/Tooltip.js","original":{"line":82,"column":42}},{"generated":{"line":105,"column":77},"source":"../src/Tooltip/Tooltip.js","original":{"line":82,"column":77}},{"name":"hide","generated":{"line":105,"column":82},"source":"../src/Tooltip/Tooltip.js","original":{"line":82,"column":82}},{"generated":{"line":105,"column":86},"source":"../src/Tooltip/Tooltip.js","original":{"line":82,"column":42}},{"generated":{"line":105,"column":87},"source":"../src/Tooltip/Tooltip.js","original":{"line":82,"column":4}},{"generated":{"line":106,"column":0},"source":"../src/Tooltip/Tooltip.js","original":{"line":83,"column":4}},{"name":"vnode","generated":{"line":106,"column":11},"source":"../src/Tooltip/Tooltip.js","original":{"line":83,"column":11}},{"generated":{"line":106,"column":16},"source":"../src/Tooltip/Tooltip.js","original":{"line":83,"column":4}},{"generated":{"line":107,"column":0},"source":"../src/Tooltip/Tooltip.js","original":{"line":84,"column":3}},{"generated":{"line":108,"column":0},"source":"../src/Tooltip/Tooltip.js","original":{"line":5,"column":15}}],"sources":{"../src/Tooltip/Tooltip.js":"import Vue from 'vue';\r\nimport TooltipContent from './TooltipContent';\r\nimport { getFirstComponentChild } from '../utils';\r\n\r\nexport default {\r\n  name: 'mu-tooltip',\r\n  props: {\r\n    content: String,\r\n    placement: TooltipContent.props.placement,\r\n    open: Boolean,\r\n    tooltipClass: [String, Object, Array]\r\n  },\r\n  data () {\r\n    return {\r\n      active: this.open,\r\n      trigger: null\r\n    };\r\n  },\r\n  beforeCreate () {\r\n    if (this.$isServer) return;\r\n\r\n    this.tooltipVM = new Vue({\r\n      data: { node: '' },\r\n      render (h) {\r\n        return this.node;\r\n      }\r\n    }).$mount();\r\n  },\r\n  mounted () {\r\n    this.trigger = this.$el;\r\n  },\r\n  methods: {\r\n    addEventHandle (old, fn) {\r\n      if (!old) {\r\n        return fn;\r\n      } else if (Array.isArray(old)) {\r\n        return old.indexOf(fn) > -1 ? old : old.concat(fn);\r\n      } else {\r\n        return old === fn ? old : [old, fn];\r\n      }\r\n    },\r\n    show () {\r\n      if (this.timer) clearTimeout(this.timer);\r\n      this.active = true;\r\n    },\r\n    hide () {\r\n      if (this.timer) clearTimeout(this.timer);\r\n      this.timer = setTimeout(() => {\r\n        this.active = false;\r\n      }, 200);\r\n    }\r\n  },\r\n  watch: {\r\n    active (val) {\r\n      this.$emit('update:open', val);\r\n    },\r\n    open (val) {\r\n      this.active = val;\r\n    }\r\n  },\r\n  render (h) {\r\n    const content = (this.$slots.content && this.$slots.content.length > 0 ? this.$slots.content : this.content) || '';\r\n    this.tooltipVM.node = h(TooltipContent, {\r\n      class: this.tooltipClass,\r\n      props: {\r\n        placement: this.placement,\r\n        open: this.active,\r\n        trigger: this.trigger\r\n      },\r\n      nativeOn: {\r\n        mouseenter: () => this.show(),\r\n        mouseleave: () => this.hide()\r\n      }\r\n    }, content);\r\n\r\n    const vnode = getFirstComponentChild(this.$slots.default);\r\n    if (!vnode) return vnode;\r\n\r\n    const on = vnode.data.on = vnode.data.on || {};\r\n    const nativeOn = vnode.data.nativeOn = vnode.data.nativeOn || {};\r\n    nativeOn.mouseenter = on.mouseenter = this.addEventHandle(on.mouseenter, this.show);\r\n    nativeOn.mouseleave = on.mouseleave = this.addEventHandle(on.mouseleave, this.hide);\r\n    return vnode;\r\n  }\r\n};\r\n"},"lineCount":null}},"hash":"9cca9b0df5aa75afee707901dc54ef3b","cacheData":{"env":{}}}